[
    {
        "Id": 1,
        "Item": "Tumbler_Phincon",
        "Price": 30000,
        "Quantity": 3,
        "Total": 90000,
        "Transaction": {
            "Id": 1,
            "TransactionNumber": 3603974259,
            "Name": "Utsman",
            "Quantity": 11,
            "Discount": 0.3,
            "Total": 336000,
            "Pay": 1000000
        }
    },
    {
        "Id": 2,
        "Item": "Kaos_Phincon_2",
        "Price": 30000,
        "Quantity": 5,
        "Total": 150000,
        "Transaction": {
            "Id": 1,
            "TransactionNumber": 3603974259,
            "Name": "Utsman",
            "Quantity": 11,
            "Discount": 0.3,
            "Total": 336000,
            "Pay": 1000000
        }
    },
    {
        "Id": 3,
        "Item": "Lanyard_Phincon_2",
        "Price": 80000,
        "Quantity": 3,
        "Total": 240000,
        "Transaction": {
            "Id": 1,
            "TransactionNumber": 3603974259,
            "Name": "Utsman",
            "Quantity": 11,
            "Discount": 0.3,
            "Total": 336000,
            "Pay": 1000000
        }
    }
]